sayn/__init__.py
sayn/cli.py
sayn/core/__init__.py
sayn/core/app.py
sayn/core/errors.py
sayn/core/project.py
sayn/core/settings.py
sayn/database/__init__.py
sayn/database/bigquery.py
sayn/database/creator.py
sayn/database/mysql.py
sayn/database/objects.py
sayn/database/postgresql.py
sayn/database/redshift.py
sayn/database/snowflake.py
sayn/database/sqlite.py
sayn/database/templates/create_table.sql
sayn/database/templates/create_view.sql
sayn/database/templates/merge_tables.sql
sayn/database/templates/move_table.sql
sayn/database/templates/redshift_load_batch.sql
sayn/database/templates/redshift_merge_tables.sql
sayn/database/templates/snowflake_create_table.sql
sayn/database/templates/snowflake_load_batch.sql
sayn/database/unknown.py
sayn/logging/__init__.py
sayn/logging/console_logger.py
sayn/logging/event_tracker.py
sayn/logging/fancy_logger.py
sayn/logging/file_logger.py
sayn/logging/log_formatter.py
sayn/logging/logger.py
sayn/logging/task_event_tracker.py
sayn/scaffolding/__init__.py
sayn/scaffolding/data/init_project/.gitignore
sayn/scaffolding/data/init_project/README.md
sayn/scaffolding/data/init_project/dev.db
sayn/scaffolding/data/init_project/prod.db
sayn/scaffolding/data/init_project/project.yaml
sayn/scaffolding/data/init_project/python/__init__.py
sayn/scaffolding/data/init_project/python/load_data.py
sayn/scaffolding/data/init_project/python/say_hello.py
sayn/scaffolding/data/init_project/requirements.txt
sayn/scaffolding/data/init_project/sample_settings.yaml
sayn/scaffolding/data/init_project/sql/dim_arenas.sql
sayn/scaffolding/data/init_project/sql/dim_fighters.sql
sayn/scaffolding/data/init_project/sql/dim_tournaments.sql
sayn/scaffolding/data/init_project/sql/f_battles.sql
sayn/scaffolding/data/init_project/sql/f_fighter_results.sql
sayn/scaffolding/data/init_project/sql/f_rankings.sql
sayn/scaffolding/init_project.py
sayn/tasks/__init__.py
sayn/tasks/autosql.py
sayn/tasks/builder.py
sayn/tasks/copy.py
sayn/tasks/dummy.py
sayn/tasks/python.py
sayn-0.6.17.dist-info/METADATA
sayn-0.6.17.dist-info/WHEEL
sayn-0.6.17.dist-info/entry_points.txt
sayn-0.6.17.dist-info/licenses/LICENSE.md
sayn-0.6.17.dist-info/licenses/NOTICE.md
sayn-0.6.17.dist-info/RECORD
