Metadata-Version: 2.4
Name: sayn
Version: 0.6.17
Summary: Data-modelling and processing framework for automating Python and SQL tasks
License: Apache-2.0
License-File: LICENSE.md
License-File: NOTICE.md
Author: Sotiris Gkoulimaris
Author-email: sotiris.gkoulimaris@173tech.com
Requires-Python: >=3.8.1,<=4.0
Classifier: License :: OSI Approved :: Apache Software License
Classifier: Programming Language :: Python :: 3
Classifier: Programming Language :: Python :: 3.9
Classifier: Programming Language :: Python :: 3.10
Classifier: Programming Language :: Python :: 3.11
Classifier: Programming Language :: Python :: 3.12
Classifier: Programming Language :: Python :: 3.13
Classifier: Programming Language :: Python :: 3.14
Provides-Extra: all
Provides-Extra: bigquery
Provides-Extra: graphviz
Provides-Extra: mysql
Provides-Extra: postgresql
Provides-Extra: postgresql-binary
Provides-Extra: redshift
Provides-Extra: snowflake
Requires-Dist: Click (==8.0.4)
Requires-Dist: Jinja2 (>=3.1.3)
Requires-Dist: PyMySQL (>=1.0.2) ; extra == "all" or extra == "mysql"
Requires-Dist: SQLAlchemy (>=1.4.25,<2.0.0)
Requires-Dist: colorama (>=0.4.4)
Requires-Dist: google-cloud-bigquery-storage (>=2.24.0,<3.0.0dev) ; extra == "bigquery"
Requires-Dist: graphviz (>=0.19.1) ; extra == "all" or extra == "all" or extra == "graphviz"
Requires-Dist: halo (==0.0.31)
Requires-Dist: orjson (>=3.9.10)
Requires-Dist: psycopg2 (>=2.9.9) ; extra == "all" or extra == "postgresql"
Requires-Dist: psycopg2-binary (>=2.9.9) ; extra == "postgresql-binary"
Requires-Dist: pydantic (>=1.9.0,<1.10.0)
Requires-Dist: redshift-connector (>=2.0.918) ; extra == "redshift"
Requires-Dist: ruamel.yaml (>=0.18.5)
Requires-Dist: ruamel.yaml.clib (>=0.2.8)
Requires-Dist: snowflake-sqlalchemy (>=1.5.1) ; extra == "all" or extra == "snowflake"
Requires-Dist: sqlalchemy-bigquery (>=1.9.0) ; extra == "all" or extra == "bigquery"
Requires-Dist: sqlalchemy-redshift (>=0.4.1) ; extra == "redshift"
Project-URL: Homepage, https://173tech.github.io/sayn
Project-URL: Repository, https://github.com/173TECH/sayn
